stkcam/__init__.py
stkcam-0.0.3.dist-info/METADATA
stkcam-0.0.3.dist-info/WHEEL
stkcam-0.0.3.dist-info/top_level.txt
stkcam-0.0.3.dist-info/RECORD
