Metadata-Version: 2.1
Name: stkcam
Version: 0.0.3
Summary: simple tinkerboard camera module
Home-page: https://github.com/harryliou/stkcam
Author: Harry Liou
Author-email: harry_liou@asus.com
Project-URL: Bug Tracker, https://github.com/harryliou/stkcam/issues
Classifier: Programming Language :: Python :: 3
Classifier: License :: OSI Approved :: MIT License
Classifier: Operating System :: OS Independent
Requires-Python: >=3.5
